COPYING.txt
MANIFEST.in
README.txt
run_archive_easy_install
run_easy_install
setup.py
mediagoblin_easy_install/__init__.py
mediagoblin_easy_install/_version.py
mediagoblin_easy_install/app.py
mediagoblin_easy_install/check.py
mediagoblin_easy_install/configs.py
mediagoblin_easy_install/instructions.py
mediagoblin_easy_install/parameters.py
mediagoblin_easy_install/tasks.py
mediagoblin_easy_install.egg-info/PKG-INFO
mediagoblin_easy_install.egg-info/SOURCES.txt
mediagoblin_easy_install.egg-info/dependency_links.txt
mediagoblin_easy_install.egg-info/requires.txt
mediagoblin_easy_install.egg-info/top_level.txt
mediagoblin_easy_install/plugins/README.txt
mediagoblin_easy_install/plugins/__init__.py
mediagoblin_easy_install/plugins/setup_archive/__init__.py
mediagoblin_easy_install/plugins/setup_archive/app.py
mediagoblin_easy_install/plugins/setup_archive/tasks.py