Metadata-Version: 1.0
Name: mediagoblin-easy-install
Version: 0.6
Summary: UNKNOWN
Home-page: http://mediagoblin.org/
Author: Free Software Foundation and contributors
Author-email: natalie.foust.pilcher@gmail.com
License: AGPLv3
Platform: UNKNOWN
